connect_four_ai-1.0.0.dist-info/METADATA
connect_four_ai-1.0.0.dist-info/WHEEL
connect_four_ai-1.0.0.dist-info/licenses/LICENSE
connect_four_ai/__init__.py
connect_four_ai/__init__.pyi
connect_four_ai/connect_four_ai.cp313-win_amd64.pyd
connect_four_ai/py.typed
connect_four_ai-1.0.0.dist-info/RECORD
