Metadata-Version: 2.4
Name: connect-four-ai
Version: 1.0.0
Classifier: License :: OSI Approved :: MIT License
Classifier: Programming Language :: Python :: 3
Classifier: Operating System :: OS Independent
License-File: LICENSE
Summary: A high performance implementation of a perfect Connect Four solver, written in Rust.
Home-Page: https://github.com/benjaminrall/connect-four-ai
Author-email: Benjamin Rall <benr2508@aol.com>
Requires-Python: >=3.13
Project-URL: Homepage, https://github.com/benjaminrall/connect-four-ai
